pyooo3/__init__.py
pyooo3-0.8.0.dist-info/METADATA
pyooo3-0.8.0.dist-info/WHEEL
pyooo3-0.8.0.dist-info/licenses/LICENSE.txt
pyooo3-0.8.0.dist-info/RECORD
